CHANGES.rst
CONTRIBUTORS.rst
DEVELOP.rst
LICENSE.rst
MANIFEST.in
README.rst
setup.cfg
setup.py
docs/conf.py
docs/index.rst
src/collective/__init__.py
src/collective.mosaictraining.egg-info/PKG-INFO
src/collective.mosaictraining.egg-info/SOURCES.txt
src/collective.mosaictraining.egg-info/dependency_links.txt
src/collective.mosaictraining.egg-info/entry_points.txt
src/collective.mosaictraining.egg-info/namespace_packages.txt
src/collective.mosaictraining.egg-info/not-zip-safe
src/collective.mosaictraining.egg-info/requires.txt
src/collective.mosaictraining.egg-info/top_level.txt
src/collective/mosaictraining/__init__.py
src/collective/mosaictraining/configure.zcml
src/collective/mosaictraining/importcontent.py
src/collective/mosaictraining/interfaces.py
src/collective/mosaictraining/permissions.zcml
src/collective/mosaictraining/setuphandlers.py
src/collective/mosaictraining/testing.py
src/collective/mosaictraining/browser/__init__.py
src/collective/mosaictraining/browser/configure.zcml
src/collective/mosaictraining/browser/images/add-page-title-field 2.png
src/collective/mosaictraining/browser/images/add-page-title-field.png
src/collective/mosaictraining/browser/images/add-tile-to-innergrid-row.png
src/collective/mosaictraining/browser/images/advanced-mode-custom-css-classes-displayed.png
src/collective/mosaictraining/browser/images/advanced-mode-custom-row-input-field.png
src/collective/mosaictraining/browser/images/content-listing-tile-listing-display-view.png
src/collective/mosaictraining/browser/images/content-listing-tile-summary-display-view.png
src/collective/mosaictraining/browser/images/content-listing-tile-tabular-display-view.png
src/collective/mosaictraining/browser/images/content-listing-tile.png
src/collective/mosaictraining/browser/images/display-menu-add-page.png
src/collective/mosaictraining/browser/images/display_menu.png
src/collective/mosaictraining/browser/images/edit-content-listing-form.png
src/collective/mosaictraining/browser/images/edit-tab.png
src/collective/mosaictraining/browser/images/format-menu-fluid.png
src/collective/mosaictraining/browser/images/initial-saved-mosaic-page.png
src/collective/mosaictraining/browser/images/insert-menu-rich-text-tile.png
src/collective/mosaictraining/browser/images/moasic-edit-toolbar-change-layout.png
src/collective/mosaictraining/browser/images/moasic-edit-toolbar-save-layout.png
