Metadata-Version: 2.1
Name: collective.mosaictraining
Version: 1.0
Summary: installs a Mosaic training guide as Plone content
Home-page: https://github.com/collective/collective.mosaictraining
Author: T. Kim Nguyen
Author-email: kim@sixfeetup.com
License: GPL version 2
Project-URL: PyPI, https://pypi.python.org/pypi/collective.mosaictraining
Project-URL: Source, https://github.com/collective/collective.mosaictraining
Project-URL: Tracker, https://github.com/collective/collective.mosaictraining/issues
Keywords: Python Plone
Platform: UNKNOWN
Classifier: Environment :: Web Environment
Classifier: Framework :: Plone
Classifier: Framework :: Plone :: Addon
Classifier: Framework :: Plone :: 5.2
Classifier: Programming Language :: Python
Classifier: Programming Language :: Python :: 2.7
Classifier: Programming Language :: Python :: 3.6
Classifier: Programming Language :: Python :: 3.7
Classifier: Operating System :: OS Independent
Classifier: License :: OSI Approved :: GNU General Public License v2 (GPLv2)
Requires-Python: ==2.7, >=3.6
Provides-Extra: test
